MsdnCBianchengZhinanCankaoshouce2015/README.md
MsdnCBianchengZhinanCankaoshouce2015/__init__.py
MsdnCBianchengZhinanCankaoshouce2015/__main__.py
MsdnCBianchengZhinanCankaoshouce2015/file.epub
MsdnCBianchengZhinanCankaoshouce2015/index.html
MsdnCBianchengZhinanCankaoshouce2015/css/__init__.py
MsdnCBianchengZhinanCankaoshouce2015/css/annotations.css
MsdnCBianchengZhinanCankaoshouce2015/css/main.css
MsdnCBianchengZhinanCankaoshouce2015/css/normalize.css
MsdnCBianchengZhinanCankaoshouce2015/css/popup.css
MsdnCBianchengZhinanCankaoshouce2015/font/__init__.py
MsdnCBianchengZhinanCankaoshouce2015/font/fontello.eot
MsdnCBianchengZhinanCankaoshouce2015/font/fontello.svg
MsdnCBianchengZhinanCankaoshouce2015/font/fontello.ttf
MsdnCBianchengZhinanCankaoshouce2015/font/fontello.woff
MsdnCBianchengZhinanCankaoshouce2015/img/__init__.py
MsdnCBianchengZhinanCankaoshouce2015/img/annotator-glyph-sprite.png
MsdnCBianchengZhinanCankaoshouce2015/img/annotator-icon-sprite.png
MsdnCBianchengZhinanCankaoshouce2015/img/apple-touch-icon.png
MsdnCBianchengZhinanCankaoshouce2015/img/cancelfullscreen.png
MsdnCBianchengZhinanCankaoshouce2015/img/close.png
MsdnCBianchengZhinanCankaoshouce2015/img/fullscreen.png
MsdnCBianchengZhinanCankaoshouce2015/img/loader.gif
MsdnCBianchengZhinanCankaoshouce2015/img/menu-icon.png
MsdnCBianchengZhinanCankaoshouce2015/img/save.png
MsdnCBianchengZhinanCankaoshouce2015/img/saved.png
MsdnCBianchengZhinanCankaoshouce2015/img/settings-s.png
MsdnCBianchengZhinanCankaoshouce2015/img/settings.png
MsdnCBianchengZhinanCankaoshouce2015/img/star.png
MsdnCBianchengZhinanCankaoshouce2015/js/__init__.py
MsdnCBianchengZhinanCankaoshouce2015/js/epub.js
MsdnCBianchengZhinanCankaoshouce2015/js/epub.min.js
MsdnCBianchengZhinanCankaoshouce2015/js/epub.min.map
MsdnCBianchengZhinanCankaoshouce2015/js/hooks.min.js
MsdnCBianchengZhinanCankaoshouce2015/js/hooks.min.map
MsdnCBianchengZhinanCankaoshouce2015/js/reader.js
MsdnCBianchengZhinanCankaoshouce2015/js/reader.js.map
msdn_c_biancheng_zhinan_cankaoshouce_2015-2024.3.2.0.dist-info/METADATA
msdn_c_biancheng_zhinan_cankaoshouce_2015-2024.3.2.0.dist-info/WHEEL
msdn_c_biancheng_zhinan_cankaoshouce_2015-2024.3.2.0.dist-info/entry_points.txt
msdn_c_biancheng_zhinan_cankaoshouce_2015-2024.3.2.0.dist-info/top_level.txt
msdn_c_biancheng_zhinan_cankaoshouce_2015-2024.3.2.0.dist-info/RECORD
